simple_h5py/__init__.py
simple_h5py/core.py
simple_h5py-0.1.2.dist-info/LICENSE
simple_h5py-0.1.2.dist-info/METADATA
simple_h5py-0.1.2.dist-info/WHEEL
simple_h5py-0.1.2.dist-info/top_level.txt
simple_h5py-0.1.2.dist-info/RECORD
