Metadata-Version: 2.1
Name: simple-h5py
Version: 0.1.2
Summary: A simple wrapper for the h5py library.
Home-page: https://github.com/amq92/simple_h5py
Author: Arturo Mendoza
License: GNU Affero General Public License v3
Platform: UNKNOWN
Classifier: Programming Language :: Python :: 3
Classifier: License :: OSI Approved :: GNU Affero General Public License v3
Classifier: Operating System :: OS Independent
Requires-Python: >=3.6
License-File: LICENSE
Requires-Dist: numpy
Requires-Dist: h5py
